clearplot/__init__.py
clearplot/axes.py
clearplot/axis_label.py
clearplot/color_bar.py
clearplot/colors.py
clearplot/custom_annotations.py
clearplot/figure.py
clearplot/params.py
clearplot/plot_functions.py
clearplot/utilities.py
clearplot/color_maps/BCC.csv
clearplot/color_maps/gray.csv
clearplot/color_maps/light_gray.csv
clearplot/color_maps/plain_blue.csv
clearplot/color_maps/plain_red.csv
clearplot/color_maps/rainbow-256.csv
clearplot/color_maps/rainbow-gray.csv
clearplot/color_maps/rainbow-no_black.csv
clearplot/color_maps/rainbow.csv
clearplot/color_maps/red_blue.csv
clearplot/color_maps/viridis.csv
clearplot/true_type_fonts/TeXGyreHerosTXfonts-Italic.ttf
clearplot/true_type_fonts/TeXGyreHerosTXfonts-Regular.ttf
clearplot-1.3.1.dist-info/licenses/LICENSE
clearplot-1.3.1.dist-info/METADATA
clearplot-1.3.1.dist-info/WHEEL
clearplot-1.3.1.dist-info/top_level.txt
clearplot-1.3.1.dist-info/RECORD
