Metadata-Version: 2.4
Name: clearplot
Version: 1.3.1
Summary: Clearplot creates publication quality plots using matplotlib
Author-email: Benjamin Reedlunn <breedlun@gmail.com>
License-Expression: MIT
Project-URL: Homepage, http://clearplot.readthedocs.org
Project-URL: Source, https://github.com/breedlun/clearplot
Keywords: matplotlib,plotting
Classifier: Development Status :: 4 - Beta
Classifier: Programming Language :: Python :: 3
Classifier: Programming Language :: Python :: 3.11
Classifier: Intended Audience :: Science/Research
Classifier: Topic :: Scientific/Engineering :: Visualization
Requires-Python: >=3.8
License-File: LICENSE
Requires-Dist: matplotlib>=3.3.0
Requires-Dist: numpy>=1.6
Dynamic: license-file
